MrLou_modules/__init__.py
MrLou_modules/Certificate_Utils/__init__.py
MrLou_modules/Certificate_Utils/cert_utils.py
MrLou_modules/Cyberark/__init__.py
MrLou_modules/Cyberark/cyberark_api.py
MrLou_modules/Cyberark/variables.py
MrLou_modules/Ping_Sweep/__init__.py
MrLou_modules/Ping_Sweep/ping_sweep.py
MrLou_modules/Random_Message/__init__.py
MrLou_modules/Random_Message/fun_facts.py
MrLou_modules/Random_Message/jokes.py
MrLou_modules/Random_Message/random_message.py
mrlou_modules-0.5.2.dist-info/METADATA
mrlou_modules-0.5.2.dist-info/WHEEL
mrlou_modules-0.5.2.dist-info/top_level.txt
mrlou_modules-0.5.2.dist-info/RECORD
