Metadata-Version: 2.1
Name: mrlou_modules
Version: 0.5.2
Summary: A package with multiple little scripts that I keep re-using
Home-page: https://github.com/lpdescamps/MrLou_modules
Author: Louis-Philippe Descamps
Author-email: me@lpdne.eu
License: UNKNOWN
Platform: UNKNOWN
Classifier: Programming Language :: Python :: 3
Classifier: License :: OSI Approved :: MIT License
Classifier: Operating System :: OS Independent
Requires-Python: >=3.6
